{
  "title": "Show #3393 - Wednesday, May 12, 1999",
  "jeopardyRound": {
    "categories": [
      "U.S. PRESIDENTS",
      "BUSINESS PARTNERS",
      "BORN IN THE WINDY CITY",
      "HIT TUNES",
      "WHAT THE KIDS ARE CALLING IT",
      "BUT IS IT ART?"
    ],
    "clues": [
      {
        "category": "U.S. PRESIDENTS",
        "value": 100,
        "question": "In 1997 a Houston airport was renamed in honor of this recent president",
        "answer": "George H.W. Bush",
        "isDailyDouble": false,
        "row": 0,
        "column": 0
      },
      {
        "category": "BUSINESS PARTNERS",
        "value": 100,
        "question": "In dessert:Burton Baskin &...",
        "answer": "Irv Robbins",
        "isDailyDouble": false,
        "row": 0,
        "column": 1
      },
      {
        "category": "BORN IN THE WINDY CITY",
        "value": 100,
        "question": "This Chicago native worked as a DJ in Vietnam & a weatherman in Nashville before hosting \"Wheel of Fortune\"",
        "answer": "Pat Sajak",
        "isDailyDouble": false,
        "row": 0,
        "column": 2
      },
      {
        "category": "HIT TUNES",
        "value": 100,
        "question": "\"Where The Streets Have No Name\",\"With Or Without You\"",
        "answer": "U2",
        "isDailyDouble": false,
        "row": 0,
        "column": 3
      },
      {
        "category": "WHAT THE KIDS ARE CALLING IT",
        "value": 100,
        "question": "On your phone & in conversation, these numbers mean information",
        "answer": "411",
        "isDailyDouble": false,
        "row": 0,
        "column": 4
      },
      {
        "category": "BUT IS IT ART?",
        "value": 100,
        "question": "It can be a gamble to hang the well-known image of dogs playing this card game",
        "answer": "Poker",
        "isDailyDouble": false,
        "row": 0,
        "column": 5
      },
      {
        "category": "U.S. PRESIDENTS",
        "value": 200,
        "question": "Nearly 91 when he died the same day as Thomas Jefferson, he was the longest-lived president",
        "answer": "John Adams",
        "isDailyDouble": false,
        "row": 1,
        "column": 0
      },
      {
        "category": "BUSINESS PARTNERS",
        "value": 200,
        "question": "In tools:Duncan Black &...",
        "answer": "Alonzo Decker",
        "isDailyDouble": false,
        "row": 1,
        "column": 1
      },
      {
        "category": "BORN IN THE WINDY CITY",
        "value": 200,
        "question": "In the film \"Animal House\", this Chicago native played wild & crazy \"Bluto\" Blutarsky",
        "answer": "John Belushi",
        "isDailyDouble": false,
        "row": 1,
        "column": 2
      },
      {
        "category": "HIT TUNES",
        "value": 200,
        "question": "\"Iris\",\"Slide\"",
        "answer": "Goo Goo Dolls",
        "isDailyDouble": false,
        "row": 1,
        "column": 3
      },
      {
        "category": "WHAT THE KIDS ARE CALLING IT",
        "value": 200,
        "question": "To Grandpa it meant he'd stirred up & fed a fire; to his grandson it means happy or excited",
        "answer": "Stoked",
        "isDailyDouble": false,
        "row": 1,
        "column": 4
      },
      {
        "category": "BUT IS IT ART?",
        "value": 200,
        "question": "The Mitchell, South Dakota \"palace\" seen here is built of & named for this cereal grain",
        "answer": "Corn",
        "isDailyDouble": false,
        "row": 1,
        "column": 5
      },
      {
        "category": "U.S. PRESIDENTS",
        "value": 600,
        "question": "It was the last name of the 17th & 36th presidents",
        "answer": "Johnson (Andrew & Lyndon)",
        "isDailyDouble": true,
        "row": 2,
        "column": 0
      },
      {
        "category": "BUSINESS PARTNERS",
        "value": 300,
        "question": "In a brokerage:William Paine &...",
        "answer": "Wallace Webber",
        "isDailyDouble": false,
        "row": 2,
        "column": 1
      },
      {
        "category": "BORN IN THE WINDY CITY",
        "value": 300,
        "question": "Tarzan was the most famous creation of this Chicago-born writer",
        "answer": "Edgar Rice Burroughs",
        "isDailyDouble": false,
        "row": 2,
        "column": 2
      },
      {
        "category": "HIT TUNES",
        "value": 300,
        "question": "\"Angel\",\"Building A Mystery\"",
        "answer": "Sarah McLachlan",
        "isDailyDouble": false,
        "row": 2,
        "column": 3
      },
      {
        "category": "WHAT THE KIDS ARE CALLING IT",
        "value": 300,
        "question": "This brand name means to eat voraciously, or to vacuum",
        "answer": "Hoover",
        "isDailyDouble": false,
        "row": 2,
        "column": 4
      },
      {
        "category": "BUT IS IT ART?",
        "value": 300,
        "question": "The work of \"Artists Barely in Control of the Brush\" is seen at Boston's MOBA, museum of this art",
        "answer": "Bad art",
        "isDailyDouble": false,
        "row": 2,
        "column": 5
      },
      {
        "category": "U.S. PRESIDENTS",
        "value": 400,
        "question": "For helping to end the Russo-Japanese War, he was awarded the 1906 Nobel Peace Prize",
        "answer": "Theodore Roosevelt",
        "isDailyDouble": false,
        "row": 3,
        "column": 0
      },
      {
        "category": "BUSINESS PARTNERS",
        "value": 400,
        "question": "In paint:Henry Sherwin &...",
        "answer": "Edward Williams",
        "isDailyDouble": false,
        "row": 3,
        "column": 1
      },
      {
        "category": "BORN IN THE WINDY CITY",
        "value": 400,
        "question": "On the big screen, this Chicagoan has played Rick Deckard, Jack Ryan & Han Solo",
        "answer": "Harrison Ford",
        "isDailyDouble": false,
        "row": 3,
        "column": 2
      },
      {
        "category": "HIT TUNES",
        "value": 400,
        "question": "\"Doo Wop (That Thing)\"",
        "answer": "Lauryn Hill",
        "isDailyDouble": false,
        "row": 3,
        "column": 3
      },
      {
        "category": "WHAT THE KIDS ARE CALLING IT",
        "value": 400,
        "question": "A sports team member who sees many women at once fits 2 definitions of this word",
        "answer": "Player",
        "isDailyDouble": false,
        "row": 3,
        "column": 4
      },
      {
        "category": "BUT IS IT ART?",
        "value": 400,
        "question": "Julian Schnabel won acclaim & abuse with his 1979 paintings that featured this tableware, broken in pieces",
        "answer": "Dishes",
        "isDailyDouble": false,
        "row": 3,
        "column": 5
      },
      {
        "category": "U.S. PRESIDENTS",
        "value": 500,
        "question": "In the campaign slogan \"Tippecanoe and Tyler Too\", he's Tippecanoe",
        "answer": "William Henry Harrison",
        "isDailyDouble": false,
        "row": 4,
        "column": 0
      },
      {
        "category": "BUSINESS PARTNERS",
        "value": 500,
        "question": "In paper products:John Kimberly &...",
        "answer": "Charles Clark",
        "isDailyDouble": false,
        "row": 4,
        "column": 1
      },
      {
        "category": "BORN IN THE WINDY CITY",
        "value": 500,
        "question": "You're keeping up with the Joneses if you name this producer of \"Thriller\" who was born in Chicago in 1933",
        "answer": "Quincy Jones",
        "isDailyDouble": false,
        "row": 4,
        "column": 2
      },
      {
        "category": "HIT TUNES",
        "value": 500,
        "question": "\"How's It Going to Be\",\"Semi-Charmed Life\"",
        "answer": "Third Eye Blind",
        "isDailyDouble": false,
        "row": 4,
        "column": 3
      },
      {
        "category": "WHAT THE KIDS ARE CALLING IT",
        "value": 500,
        "question": "\"What An Appealing Young Lady\" can be translated to this title of a 1999 movie",
        "answer": "She's All That",
        "isDailyDouble": false,
        "row": 4,
        "column": 4
      },
      {
        "category": "BUT IS IT ART?",
        "value": 500,
        "question": "Tattooed showman The Enigma had tiny versions of these embedded in his skull, perhaps for a Satanic look",
        "answer": "Horns",
        "isDailyDouble": false,
        "row": 4,
        "column": 5
      }
    ]
  },
  "doubleJeopardyRound": {
    "categories": [
      "ROAMIN' THE WORLD",
      "GREEK LIFE",
      "CARIBBEAN TASTE TREATS",
      "THE 12 TRIBES OF ISRAEL",
      "ENGLISH ROYAL HENRYS",
      "PARDON MY \"FRENCH\""
    ],
    "clues": [
      {
        "category": "ROAMIN' THE WORLD",
        "value": 200,
        "question": "About two-thirds of this U.K. country's area is in its highlands & islands",
        "answer": "Scotland",
        "isDailyDouble": false,
        "row": 0,
        "column": 0
      },
      {
        "category": "GREEK LIFE",
        "value": 200,
        "question": "This best-known Greek cheese, from the milk of sheep & goats, has been made for thousands of years",
        "answer": "Feta",
        "isDailyDouble": false,
        "row": 0,
        "column": 1
      },
      {
        "category": "CARIBBEAN TASTE TREATS",
        "value": 200,
        "question": "Sancocho, a stew made with 5 to 7 meats, is a specialty of this country, Haiti's next-door neighbor",
        "answer": "Dominican Republic",
        "isDailyDouble": false,
        "row": 0,
        "column": 2
      },
      {
        "category": "THE 12 TRIBES OF ISRAEL",
        "value": 200,
        "question": "Football great Dierdorf",
        "answer": "Dan",
        "isDailyDouble": false,
        "row": 0,
        "column": 3
      },
      {
        "category": "ENGLISH ROYAL HENRYS",
        "value": 200,
        "question": "Henry I's famous father was this conqueror who reigned from 1066 to 1087",
        "answer": "William the Conqueror",
        "isDailyDouble": false,
        "row": 0,
        "column": 4
      },
      {
        "category": "PARDON MY \"FRENCH\"",
        "value": 200,
        "question": "Settlers began living in this section of New Orleans in the early 18th century",
        "answer": "French Quarter",
        "isDailyDouble": false,
        "row": 0,
        "column": 5
      },
      {
        "category": "ROAMIN' THE WORLD",
        "value": 400,
        "question": "When Sudan takes you to a place by this river, you can sit by the Blue or White one",
        "answer": "Nile",
        "isDailyDouble": false,
        "row": 1,
        "column": 0
      },
      {
        "category": "GREEK LIFE",
        "value": 400,
        "question": "98% of Greece's population belongs to this church",
        "answer": "Greek",
        "isDailyDouble": false,
        "row": 1,
        "column": 1
      },
      {
        "category": "CARIBBEAN TASTE TREATS",
        "value": 400,
        "question": "Don't worry if you see this word on a Barbados menu: it refers to a fish, not the star of \"Flipper\"",
        "answer": "Dolphin",
        "isDailyDouble": false,
        "row": 1,
        "column": 2
      },
      {
        "category": "THE 12 TRIBES OF ISRAEL",
        "value": 400,
        "question": "\"Law & Order\" actor Bratt",
        "answer": "Benjamin",
        "isDailyDouble": false,
        "row": 1,
        "column": 3
      },
      {
        "category": "ENGLISH ROYAL HENRYS",
        "value": 400,
        "question": "Pope Leo X named Henry VIII \"Defender of the Faith\" for his written attack on this German Protestant leader",
        "answer": "Martin Luther",
        "isDailyDouble": false,
        "row": 1,
        "column": 4
      },
      {
        "category": "PARDON MY \"FRENCH\"",
        "value": 400,
        "question": "In a French restaurant, they're called pommes frites",
        "answer": "French fries",
        "isDailyDouble": false,
        "row": 1,
        "column": 5
      },
      {
        "category": "ROAMIN' THE WORLD",
        "value": 600,
        "question": "Pier 21, considered \"Canada's Ellis Island\", is in this Nova Scotia city",
        "answer": "Halifax",
        "isDailyDouble": false,
        "row": 2,
        "column": 0
      },
      {
        "category": "GREEK LIFE",
        "value": 600,
        "question": "Greek cafe music features a lute called a bouzouki & this woodwind, the klarino",
        "answer": "Clarinet",
        "isDailyDouble": false,
        "row": 2,
        "column": 1
      },
      {
        "category": "CARIBBEAN TASTE TREATS",
        "value": 600,
        "question": "If you order \"mountain chicken\" in Dominica, you won't get chicken but one of these amphibians",
        "answer": "Frogs",
        "isDailyDouble": false,
        "row": 2,
        "column": 2
      },
      {
        "category": "THE 12 TRIBES OF ISRAEL",
        "value": 600,
        "question": "Jeans maker Strauss",
        "answer": "Levi",
        "isDailyDouble": false,
        "row": 2,
        "column": 3
      },
      {
        "category": "ENGLISH ROYAL HENRYS",
        "value": 600,
        "question": "King Henry III extensively rebuilt this abbey where he had been formally crowned in 1220",
        "answer": "Westminster Abbey",
        "isDailyDouble": false,
        "row": 2,
        "column": 4
      },
      {
        "category": "PARDON MY \"FRENCH\"",
        "value": 600,
        "question": "In France this musical instrument is called \"cor d' harmonie\"",
        "answer": "French horn",
        "isDailyDouble": false,
        "row": 2,
        "column": 5
      },
      {
        "category": "ROAMIN' THE WORLD",
        "value": 800,
        "question": "Tea & coconuts are top products of this country, the \"Pearl of the Indian Ocean\"",
        "answer": "Sri Lanka",
        "isDailyDouble": false,
        "row": 3,
        "column": 0
      },
      {
        "category": "GREEK LIFE",
        "value": 800,
        "question": "Crowds flock to Dodona, Philippi & Thassos to see festivals of this art performed in ancient venues",
        "answer": "Theater",
        "isDailyDouble": false,
        "row": 3,
        "column": 1
      },
      {
        "category": "CARIBBEAN TASTE TREATS",
        "value": 800,
        "question": "Adventurous eaters in Grenada may dine on this burrowing mammal (it's best to remove the armor first)",
        "answer": "Armadillo",
        "isDailyDouble": false,
        "row": 3,
        "column": 2
      },
      {
        "category": "THE 12 TRIBES OF ISRAEL",
        "value": 800,
        "question": "Novelist Heller",
        "answer": "Joseph",
        "isDailyDouble": false,
        "row": 3,
        "column": 3
      },
      {
        "category": "ENGLISH ROYAL HENRYS",
        "value": 800,
        "question": "Victory at Agincourt in 1415 earned this king a visit from the Holy Roman Emperor",
        "answer": "Henry V",
        "isDailyDouble": false,
        "row": 3,
        "column": 4
      },
      {
        "category": "PARDON MY \"FRENCH\"",
        "value": 800,
        "question": "It was waged in North America from 1754 to 1763",
        "answer": "French and Indian War",
        "isDailyDouble": false,
        "row": 3,
        "column": 5
      },
      {
        "category": "ROAMIN' THE WORLD",
        "value": 2000,
        "question": "In 1991 the Yanomami tribe in this country was awarded a reserve 3 times the size of Belgium",
        "answer": "Brazil",
        "isDailyDouble": true,
        "row": 4,
        "column": 0
      },
      {
        "category": "GREEK LIFE",
        "value": 1000,
        "question": "Patricia Storace titled her 1996 book on travels in Greece \"Dinner with\" this goddess of the underworld",
        "answer": "Persephone",
        "isDailyDouble": false,
        "row": 4,
        "column": 1
      },
      {
        "category": "CARIBBEAN TASTE TREATS",
        "value": 1000,
        "question": "Puerto Ricans love to drink the juice of this fruit they call parcha -- maybe it makes them feel \"amorous\"",
        "answer": "Passion fruit",
        "isDailyDouble": false,
        "row": 4,
        "column": 2
      },
      {
        "category": "THE 12 TRIBES OF ISRAEL",
        "value": 1000,
        "question": "Explorer Pike",
        "answer": "Zebulon",
        "isDailyDouble": false,
        "row": 4,
        "column": 3
      },
      {
        "category": "ENGLISH ROYAL HENRYS",
        "value": 2000,
        "question": "These 2 warring royal houses were united in 1486 when Henry VII married Elizabeth, the daughter of Edward IV",
        "answer": "Lancaster & York",
        "isDailyDouble": true,
        "row": 4,
        "column": 4
      },
      {
        "category": "PARDON MY \"FRENCH\"",
        "value": 1000,
        "question": "They're formed by folding back & fastening a wide band at the end of a sleeve",
        "answer": "French cuffs",
        "isDailyDouble": false,
        "row": 4,
        "column": 5
      }
    ]
  },
  "finalJeopardy": {
    "category": "RENAISSANCE LITERATURE",
    "clue": "This book begins, \"All states and dominions which hold or have held mankind are either republics or monarchies\"",
    "answer": "\"The Prince\" (by Machiavelli)"
  },
  "gameId": "3393",
  "gameDate": "Wednesday, May 12, 1999"
}